pwsAI/NIS_Naming_Script.py
pwsAI/__init__.py
pwsAI/__main__.py
pwsAI/autoSegCube.py
pwsAI/convertNuc.py
pwsAI/convertRMS.py
pwsAI/regular_unet.py
pwsAI/selectFolder.py
pwsAI/t.py
pwsAI/_resources/PWS_with_augmentation_weights_minmax_norm_ali_roi_updated_522_images_bf_rms_sw_patch512_100_epoches.hdf5
pwsAI-0.2.0.0.dist-info/METADATA
pwsAI-0.2.0.0.dist-info/WHEEL
pwsAI-0.2.0.0.dist-info/entry_points.txt
pwsAI-0.2.0.0.dist-info/top_level.txt
pwsAI-0.2.0.0.dist-info/RECORD
