Metadata-Version: 2.1
Name: pwsAI
Version: 0.2.0.0
Summary: A GUI for AI segmentation of cell imagery.
Home-page: https://github.com/nanthony21/pws_AI
Author: Nico Acosta
Author-email: nicolasacosta2026@u.northwestern.edu
Requires-Python: >=3.7
Requires-Dist: numpy
Requires-Dist: matplotlib
Requires-Dist: PySimpleGUI ==4.50.0
Requires-Dist: pwspy
Requires-Dist: pillow
Requires-Dist: scikit-image
Requires-Dist: scikit-learn
Requires-Dist: tifffile
Requires-Dist: opencv-python
Requires-Dist: patchify
Requires-Dist: h5py
Requires-Dist: rasterio
Requires-Dist: tensorflow ==2.6.2
Requires-Dist: protobuf <=3.19.6
